forging_blocks/__init__.py
forging_blocks/application/README.md
forging_blocks/application/__init__.py
forging_blocks/application/ports/__init__.py
forging_blocks/application/ports/inbound/__init__.py
forging_blocks/application/ports/inbound/message_handler.py
forging_blocks/application/ports/inbound/use_case.py
forging_blocks/application/ports/outbound/__init__.py
forging_blocks/application/ports/outbound/command_sender.py
forging_blocks/application/ports/outbound/event_publisher.py
forging_blocks/application/ports/outbound/message_bus.py
forging_blocks/application/ports/outbound/notifier.py
forging_blocks/application/ports/outbound/query_fetcher.py
forging_blocks/application/ports/outbound/repository.py
forging_blocks/application/ports/outbound/unit_of_work.py
forging_blocks/domain/README.md
forging_blocks/domain/__init__.py
forging_blocks/domain/aggregate_root.py
forging_blocks/domain/entity.py
forging_blocks/domain/errors/__init__.py
forging_blocks/domain/errors/draft_entity_is_not_hashable_error.py
forging_blocks/domain/errors/entity_id_none_error.py
forging_blocks/domain/messages/__init__.py
forging_blocks/domain/messages/command.py
forging_blocks/domain/messages/event.py
forging_blocks/domain/messages/message.py
forging_blocks/domain/messages/query.py
forging_blocks/domain/value_object.py
forging_blocks/foundation/__init__.py
forging_blocks/foundation/debuggable.py
forging_blocks/foundation/errors/__init__.py
forging_blocks/foundation/errors/base.py
forging_blocks/foundation/errors/cant_modify_immutable_attribute_error.py
forging_blocks/foundation/errors/core.py
forging_blocks/foundation/errors/rule_violation_error.py
forging_blocks/foundation/errors/validation_error.py
forging_blocks/foundation/mapper.py
forging_blocks/foundation/meta/__init__.py
forging_blocks/foundation/meta/final_meta.py
forging_blocks/foundation/ports.py
forging_blocks/foundation/result.py
forging_blocks/foundation/result_mapper.py
forging_blocks/infrastructure/README.md
forging_blocks-0.3.6.dist-info/LICENSE
forging_blocks-0.3.6.dist-info/METADATA
forging_blocks-0.3.6.dist-info/WHEEL
forging_blocks-0.3.6.dist-info/RECORD
