Metadata-Version: 2.1
Name: forging-blocks
Version: 0.3.6
Summary: Composable toolkit for clean, testable, and maintainable Python applications
Home-page: https://forging-blocks-org.github.io/forging-blocks/
License: MIT
Keywords: python library,clean architecture,hexagonal architecture,domain-driven design,ddd,framework-agnostic,software architecture,software design,software engineering,ports and adapters,adapter pattern,application service,repository pattern,message bus,notifier pattern,data mapper,result pattern,result monad,ok,err,either type,debuggable,use case,domain layer,application layer,presentation layer,foundation,forging blocks
Author: ForgingBlocks Org
Author-email: forgingblocksorganization91@gmail.com
Requires-Python: >=3.12,<4.0
Classifier: License :: OSI Approved :: MIT License
Classifier: Programming Language :: Python :: 3
Classifier: Programming Language :: Python :: 3.12
Project-URL: Repository, https://github.com/forging-blocks-org/forging-blocks
